LICENSE
MANIFEST.in
README.md
requirements.txt
setup.cfg
setup.py
flaskapptestjw/__init__.py
flaskapptestjw/config.py
flaskapptestjw/hello.py
flaskapptestjw/test1.py
flaskapptestjw/test10.py
flaskapptestjw/test11.py
flaskapptestjw/test12.py
flaskapptestjw/test13.py
flaskapptestjw/test14.py
flaskapptestjw/test15.py
flaskapptestjw/test16.py
flaskapptestjw/test17.py
flaskapptestjw/test18.py
flaskapptestjw/test19.py
flaskapptestjw/test2.py
flaskapptestjw/test20.py
flaskapptestjw/test3.py
flaskapptestjw/test4.py
flaskapptestjw/test5.py
flaskapptestjw/test6.py
flaskapptestjw/test7.py
flaskapptestjw/test8.py
flaskapptestjw/test9.py
flaskapptestjw.egg-info/PKG-INFO
flaskapptestjw.egg-info/SOURCES.txt
flaskapptestjw.egg-info/dependency_links.txt
flaskapptestjw.egg-info/not-zip-safe
flaskapptestjw.egg-info/requires.txt
flaskapptestjw.egg-info/top_level.txt
flaskapptestjw/shell_scripts/test.ipynb
flaskapptestjw/shell_scripts/test.sh
flaskapptestjw/shell_scripts/test10.ipynb
flaskapptestjw/shell_scripts/test11.ipynb
flaskapptestjw/shell_scripts/test12.ipynb
flaskapptestjw/shell_scripts/test13.ipynb
flaskapptestjw/shell_scripts/test14.ipynb
flaskapptestjw/shell_scripts/test15.ipynb
flaskapptestjw/shell_scripts/test16.ipynb
flaskapptestjw/shell_scripts/test17.ipynb
flaskapptestjw/shell_scripts/test18.ipynb
flaskapptestjw/shell_scripts/test19.ipynb
flaskapptestjw/shell_scripts/test2.ipynb
flaskapptestjw/shell_scripts/test20.ipynb
flaskapptestjw/shell_scripts/test3.ipynb
flaskapptestjw/shell_scripts/test4.ipynb
flaskapptestjw/shell_scripts/test5.ipynb
flaskapptestjw/shell_scripts/test6.ipynb
flaskapptestjw/shell_scripts/test7.ipynb
flaskapptestjw/shell_scripts/test8.ipynb
flaskapptestjw/shell_scripts/test9.ipynb
flaskapptestjw/templates/index.html