Metadata-Version: 1.0
Name: flaskapptestjw
Version: 0.13
Summary: Test Flask app upload with pypi
Home-page: UNKNOWN
Author: jwhan
Author-email: UNKNOWN
License: UNKNOWN
Platform: UNKNOWN
